transstellar/__init__.py
transstellar/api_client/__init__.py
transstellar/api_client/api_client.py
transstellar/api_client/api_resource.py
transstellar/api_client/errors/__init__.py
transstellar/api_client/errors/client_error.py
transstellar/api_client/errors/server_error.py
transstellar/api_client/errors/unauthorized_error.py
transstellar/framework/__init__.py
transstellar/framework/application.py
transstellar/framework/application_bootstrapper.py
transstellar/framework/base_api_test.py
transstellar/framework/base_page.py
transstellar/framework/base_test.py
transstellar/framework/base_ui_test.py
transstellar/framework/config_service.py
transstellar/framework/decorators/handle_error.py
transstellar/framework/decorators/handle_ui_error.py
transstellar/framework/decorators/with_timeout.py
transstellar/framework/element.py
transstellar/framework/handle_page_error.py
transstellar/framework/loggable.py
transstellar/framework/logger.py
transstellar/framework/main_config.py
transstellar/framework/module.py
transstellar/framework/page_decorator_meta.py
transstellar/framework/route.py
transstellar/framework/router.py
transstellar/framework/utils.py
transstellar/html/__init__.py
transstellar/html/a.py
transstellar/html/body.py
transstellar/html/button.py
transstellar/html/div.py
transstellar/html/h1.py
transstellar/html/h2.py
transstellar/html/header.py
transstellar/html/image.py
transstellar/html/input.py
transstellar/html/li.py
transstellar/html/p.py
transstellar/html/span.py
transstellar/html/ul.py
transstellar-3.12.1.dist-info/METADATA
transstellar-3.12.1.dist-info/WHEEL
transstellar-3.12.1.dist-info/RECORD
